<?xml version="1.0" encoding="UTF-8" standalone="yes"?>
<?mso-application progid="Word.Document"?>
<w:wordDocument xmlns:w="http://schemas.microsoft.com/office/word/2003/wordml" xmlns:v="urn:schemas-microsoft-com:vml" xmlns:w10="urn:schemas-microsoft-com:office:word" xmlns:sl="http://schemas.microsoft.com/schemaLibrary/2003/core" xmlns:aml="http://schemas.microsoft.com/aml/2001/core" xmlns:wx="http://schemas.microsoft.com/office/word/2003/auxHint" xmlns:o="urn:schemas-microsoft-com:office:office" xmlns:dt="uuid:C2F41010-65B3-11d1-A29F-00AA00C14882" xmlns:wsp="http://schemas.microsoft.com/office/word/2003/wordml/sp2" xmlns:st1="urn:schemas-microsoft-com:office:smarttags" w:macrosPresent="no" w:embeddedObjPresent="no" w:ocxPresent="no" xml:space="preserve"><w:ignoreElements w:val="http://schemas.microsoft.com/office/word/2003/wordml/sp2"/><o:SmartTagType o:namespaceuri="urn:schemas-microsoft-com:office:smarttags" o:name="PostalCode"/><o:SmartTagType o:namespaceuri="urn:schemas-microsoft-com:office:smarttags" o:name="State"/><o:SmartTagType o:namespaceuri="urn:schemas-microsoft-com:office:smarttags" o:name="City"/><o:SmartTagType o:namespaceuri="urn:schemas-microsoft-com:office:smarttags" o:name="place"/><o:SmartTagType o:namespaceuri="urn:schemas-microsoft-com:office:smarttags" o:name="PlaceName"/><o:DocumentProperties><o:Title>HARRIS COUNTY OFFICE OF COURT SERVICES</o:Title><o:Author>Mara_Porper</o:Author><o:LastAuthor>kmurthy</o:LastAuthor><o:Revision>22</o:Revision><o:TotalTime>13</o:TotalTime><o:LastPrinted>2005-02-10T18:58:00Z</o:LastPrinted><o:Created>2006-07-31T21:09:00Z</o:Created><o:LastSaved>2006-08-09T15:44:00Z</o:LastSaved><o:Pages>1</o:Pages><o:Words>564</o:Words><o:Characters>3221</o:Characters><o:Company>PTSA</o:Company><o:Lines>26</o:Lines><o:Paragraphs>7</o:Paragraphs><o:CharactersWithSpaces>3778</o:CharactersWithSpaces><o:Version>11.8026</o:Version></o:DocumentProperties><w:fonts><w:defaultFonts w:ascii="Times New Roman" w:fareast="Times New Roman" w:h-ansi="Times New Roman" w:cs="Times New Roman"/><w:font w:name="MS Shell Dlg"><w:panose-1 w:val="020B0604020202020204"/><w:charset w:val="00"/><w:family w:val="Swiss"/><w:pitch w:val="variable"/><w:sig w:usb-0="61007BDF" w:usb-1="80000000" w:usb-2="00000008" w:usb-3="00000000" w:csb-0="000101FF" w:csb-1="00000000"/></w:font></w:fonts><w:styles><w:versionOfBuiltInStylenames w:val="4"/><w:latentStyles w:defLockedState="off" w:latentStyleCount="156"/><w:style w:type="paragraph" w:default="on" w:styleId="Normal"><w:name w:val="Normal"/><w:rsid w:val="00FE035B"/><w:rPr><wx:font wx:val="Times New Roman"/><w:lang w:val="EN-US" w:fareast="EN-US" w:bidi="AR-SA"/></w:rPr></w:style><w:style w:type="paragraph" w:styleId="Heading1"><w:name w:val="heading 1"/><wx:uiName wx:val="Heading 1"/><w:basedOn w:val="Normal"/><w:next w:val="Normal"/><w:rsid w:val="00FE035B"/><w:pPr><w:pStyle w:val="Heading1"/><w:keepNext/><w:jc w:val="center"/><w:outlineLvl w:val="0"/></w:pPr><w:rPr><wx:font wx:val="Times New Roman"/><w:sz w:val="24"/></w:rPr></w:style><w:style w:type="paragraph" w:styleId="Heading2"><w:name w:val="heading 2"/><wx:uiName wx:val="Heading 2"/><w:basedOn w:val="Normal"/><w:next w:val="Normal"/><w:rsid w:val="00FE035B"/><w:pPr><w:pStyle w:val="Heading2"/><w:keepNext/><w:jc w:val="center"/><w:outlineLvl w:val="1"/></w:pPr><w:rPr><wx:font wx:val="Times New Roman"/><w:b/><w:b-cs/><w:sz w:val="28"/></w:rPr></w:style><w:style w:type="character" w:default="on" w:styleId="DefaultParagraphFont"><w:name w:val="Default Paragraph Font"/><w:semiHidden/></w:style><w:style w:type="table" w:default="on" w:styleId="TableNormal"><w:name w:val="Normal Table"/><wx:uiName wx:val="Table Normal"/><w:semiHidden/><w:rPr><wx:font wx:val="Times New Roman"/></w:rPr><w:tblPr><w:tblInd w:w="0" w:type="dxa"/><w:tblCellMar><w:top w:w="0" w:type="dxa"/><w:left w:w="108" w:type="dxa"/><w:bottom w:w="0" w:type="dxa"/><w:right w:w="108" w:type="dxa"/></w:tblCellMar></w:tblPr></w:style><w:style w:type="list" w:default="on" w:styleId="NoList"><w:name w:val="No List"/><w:semiHidden/></w:style><w:style w:type="paragraph" w:styleId="Header"><w:name w:val="header"/><wx:uiName wx:val="Header"/><w:basedOn w:val="Normal"/><w:rsid w:val="00FE035B"/><w:pPr><w:pStyle w:val="Header"/><w:tabs><w:tab w:val="center" w:pos="4320"/><w:tab w:val="right" w:pos="8640"/></w:tabs></w:pPr><w:rPr><wx:font wx:val="Times New Roman"/></w:rPr></w:style><w:style w:type="paragraph" w:styleId="Footer"><w:name w:val="footer"/><wx:uiName wx:val="Footer"/><w:basedOn w:val="Normal"/><w:rsid w:val="00FE035B"/><w:pPr><w:pStyle w:val="Footer"/><w:tabs><w:tab w:val="center" w:pos="4320"/><w:tab w:val="right" w:pos="8640"/></w:tabs></w:pPr><w:rPr><wx:font wx:val="Times New Roman"/></w:rPr></w:style></w:styles><w:docPr><w:view w:val="print"/><w:zoom w:percent="100"/><w:attachedTemplate w:val=""/><w:defaultTabStop w:val="720"/><w:displayHorizontalDrawingGridEvery w:val="0"/><w:displayVerticalDrawingGridEvery w:val="0"/><w:useMarginsForDrawingGridOrigin/><w:characterSpacingControl w:val="DontCompress"/><w:optimizeForBrowser/><w:validateAgainstSchema/><w:saveInvalidXML w:val="off"/><w:ignoreMixedContent w:val="off"/><w:alwaysShowPlaceholderText w:val="off"/><w:footnotePr><w:footnote w:type="separator"><w:p wsp:rsidR="009E5B50" wsp:rsidRDefault="009E5B50"><w:r><w:separator/></w:r></w:p></w:footnote><w:footnote w:type="continuation-separator"><w:p wsp:rsidR="009E5B50" wsp:rsidRDefault="009E5B50"><w:r><w:continuationSeparator/></w:r></w:p></w:footnote></w:footnotePr><w:endnotePr><w:endnote w:type="separator"><w:p wsp:rsidR="009E5B50" wsp:rsidRDefault="009E5B50"><w:r><w:separator/></w:r></w:p></w:endnote><w:endnote w:type="continuation-separator"><w:p wsp:rsidR="009E5B50" wsp:rsidRDefault="009E5B50"><w:r><w:continuationSeparator/></w:r></w:p></w:endnote></w:endnotePr><w:compat><w:footnoteLayoutLikeWW8/><w:shapeLayoutLikeWW8/><w:alignTablesRowByRow/><w:forgetLastTabAlignment/><w:doNotUseHTMLParagraphAutoSpacing/><w:layoutRawTableWidth/><w:layoutTableRowsApart/><w:useWord97LineBreakingRules/><w:dontAllowFieldEndSelect/><w:useWord2002TableStyleRules/></w:compat><wsp:rsids><wsp:rsidRoot wsp:val="007C4439"/><wsp:rsid wsp:val="000079DD"/><wsp:rsid wsp:val="00040FDC"/><wsp:rsid wsp:val="00102FB1"/><wsp:rsid wsp:val="001713E9"/><wsp:rsid wsp:val="001741A0"/><wsp:rsid wsp:val="001F045E"/><wsp:rsid wsp:val="002230AA"/><wsp:rsid wsp:val="00297A1B"/><wsp:rsid wsp:val="00301BF4"/><wsp:rsid wsp:val="00333985"/><wsp:rsid wsp:val="00345D88"/><wsp:rsid wsp:val="003A541E"/><wsp:rsid wsp:val="003D1C1B"/><wsp:rsid wsp:val="004879F4"/><wsp:rsid wsp:val="00496B62"/><wsp:rsid wsp:val="005D03F8"/><wsp:rsid wsp:val="006451B0"/><wsp:rsid wsp:val="006C1A58"/><wsp:rsid wsp:val="007A0BE1"/><wsp:rsid wsp:val="007C4439"/><wsp:rsid wsp:val="008D71F5"/><wsp:rsid wsp:val="00956BD4"/><wsp:rsid wsp:val="009B5264"/><wsp:rsid wsp:val="009E5B50"/><wsp:rsid wsp:val="00A43F29"/><wsp:rsid wsp:val="00A526DC"/><wsp:rsid wsp:val="00A65035"/><wsp:rsid wsp:val="00B701A8"/><wsp:rsid wsp:val="00B954BA"/><wsp:rsid wsp:val="00BA45F4"/><wsp:rsid wsp:val="00BD772B"/><wsp:rsid wsp:val="00C101FD"/><wsp:rsid wsp:val="00C87E39"/><wsp:rsid wsp:val="00DF5A36"/><wsp:rsid wsp:val="00E50DAE"/><wsp:rsid wsp:val="00E66B63"/><wsp:rsid wsp:val="00E67407"/><wsp:rsid wsp:val="00E9711F"/><wsp:rsid wsp:val="00F52FB7"/><wsp:rsid wsp:val="00F671C6"/><wsp:rsid wsp:val="00F705EF"/><wsp:rsid wsp:val="00FE035B"/></wsp:rsids></w:docPr><w:body><wx:sect><w:p wsp:rsidR="004879F4" wsp:rsidRDefault="004879F4"><w:pPr><w:jc w:val="center"/><w:rPr><w:sz w:val="24"/></w:rPr></w:pPr><st1:place w:st="on"><st1:PlaceName w:st="on"><w:r><w:rPr><w:sz w:val="24"/></w:rPr><w:t>HARRIS</w:t></w:r></st1:PlaceName><w:r><w:rPr><w:sz w:val="24"/></w:rPr><w:t> </w:t></w:r><st1:PlaceName w:st="on"><w:r><w:rPr><w:sz w:val="24"/></w:rPr><w:t>COUNTY</w:t></w:r></st1:PlaceName></st1:place><w:r><w:rPr><w:sz w:val="24"/></w:rPr><w:t> PRETRIAL SERVICES</w:t></w:r></w:p><w:p wsp:rsidR="004879F4" wsp:rsidRDefault="004879F4"><w:pPr><w:jc w:val="center"/><w:rPr><w:sz w:val="24"/></w:rPr></w:pPr><w:r><w:rPr><w:sz w:val="24"/></w:rPr><w:t>1201 </w:t></w:r><st1:place w:st="on"><st1:City w:st="on"><w:r><w:rPr><w:sz w:val="24"/></w:rPr><w:t>Franklin</w:t></w:r></st1:City></st1:place><w:r><w:rPr><w:sz w:val="24"/></w:rPr><w:t>, 12</w:t></w:r><w:r><w:rPr><w:sz w:val="24"/><w:vertAlign w:val="superscript"/></w:rPr><w:t>th</w:t></w:r><w:r><w:rPr><w:sz w:val="24"/></w:rPr><w:t> Floor</w:t></w:r></w:p><wx:sub-section><w:p wsp:rsidR="004879F4" wsp:rsidRDefault="004879F4"><w:pPr><w:pStyle w:val="Heading1"/></w:pPr><st1:place w:st="on"><st1:City w:st="on"><w:r><w:t>Houston</w:t></w:r></st1:City><w:r><w:t>, </w:t></w:r><st1:State w:st="on"><w:r><w:t>Texas</w:t></w:r></st1:State><w:r><w:t> </w:t></w:r><st1:PostalCode w:st="on"><w:r><w:t>77002</w:t></w:r></st1:PostalCode></st1:place></w:p><w:p wsp:rsidR="004879F4" wsp:rsidRDefault="004879F4"><w:pPr><w:jc w:val="center"/></w:pPr></w:p><w:p wsp:rsidR="004879F4" wsp:rsidRPr="007C4439" wsp:rsidRDefault="004879F4" wsp:rsidP="007C4439"><w:pPr><w:tabs><w:tab w:val="center" w:pos="4580"/></w:tabs><w:jc w:val="center"/><w:rPr><w:b/><w:b-cs/><w:sz w:val="24"/><w:sz-cs w:val="24"/></w:rPr></w:pPr><w:r wsp:rsidRPr="007C4439"><w:rPr><w:b/><w:sz w:val="24"/><w:sz-cs w:val="24"/></w:rPr><w:t>PERSONAL BOND</w:t></w:r></w:p><w:p wsp:rsidR="007C4439" wsp:rsidRDefault="007C4439" wsp:rsidP="007C4439"><w:pPr><w:tabs><w:tab w:val="left" w:pos="7920"/><w:tab w:val="right" w:pos="10710"/></w:tabs><w:spacing w:line="300" w:line-rule="exact"/></w:pPr><w:r><w:t>THE STATE OF </w:t></w:r><st1:place w:st="on"><st1:State w:st="on"><w:r><w:t>TEXAS</w:t></w:r></st1:State></st1:place><w:r><w:tab wx:wTab="5970" wx:tlc="none" wx:cTlc="132"/><w:t>CAUSE NO. </w:t></w:r><w:r wsp:rsidR="00B701A8" wsp:rsidRPr="00B701A8"><w:rPr><w:b/><w:u w:val="single"/></w:rPr><w:t>[Cause]</w:t></w:r><w:r wsp:rsidR="00F671C6" wsp:rsidRPr="001713E9"><w:rPr><w:b/><w:u w:val="single"/></w:rPr><w:t> </w:t></w:r></w:p><w:p wsp:rsidR="007C4439" wsp:rsidRDefault="007C4439" wsp:rsidP="007C4439"><w:pPr><w:tabs><w:tab w:val="right" w:pos="10710"/></w:tabs><w:spacing w:line="240" w:line-rule="exact"/><w:jc w:val="center"/></w:pPr><w:r><w:t>KNOW ALL MEN BY THESE PRESENTS</w:t></w:r></w:p><w:p wsp:rsidR="007C4439" wsp:rsidRDefault="007C4439" wsp:rsidP="007C4439"><w:pPr><w:tabs><w:tab w:val="left" w:pos="7920"/><w:tab w:val="right" w:pos="10710"/></w:tabs><w:spacing w:line="300" w:line-rule="exact"/></w:pPr><w:r><w:t>COUNTY OF HARRIS</w:t></w:r><w:r><w:tab wx:wTab="6135" wx:tlc="none" wx:cTlc="135"/><w:t>SPN </w:t></w:r><w:r wsp:rsidR="009B5264" wsp:rsidRPr="009B5264"><w:rPr><w:b/><w:noProof/><w:u w:val="single"/></w:rPr><w:t>[SPN]</w:t></w:r></w:p><w:p wsp:rsidR="004879F4" wsp:rsidRDefault="007C4439" wsp:rsidP="00A65035"><w:pPr><w:tabs><w:tab w:val="center" w:pos="4580"/></w:tabs></w:pPr><w:r><w:t>THAT I, </w:t></w:r><w:r wsp:rsidR="00E50DAE" wsp:rsidRPr="00A65035"><w:rPr><w:b/><w:noProof/><w:u w:val="single"/></w:rPr><w:t>[Name]</w:t></w:r><w:r wsp:rsidR="00E50DAE"><w:t> </w:t></w:r><w:r><w:t>convicted of the offense of </w:t></w:r><w:r wsp:rsidR="00E50DAE"><w:t> </w:t></w:r><w:r wsp:rsidR="00E50DAE" wsp:rsidRPr="00A65035"><w:rPr><w:b/><w:b-cs/><w:u w:val="single"/></w:rPr><w:t>[OffenseLevel] </w:t></w:r><w:r wsp:rsidR="00333985" wsp:rsidRPr="00333985"><w:rPr><w:b/><w:u w:val="single"/></w:rPr><w:t>[Offense]</w:t></w:r><w:r wsp:rsidR="00333985"><w:rPr><w:rFonts w:ascii="Arial" w:h-ansi="Arial" w:cs="Arial"/><wx:font wx:val="Arial"/><w:u w:val="single"/></w:rPr><w:t> </w:t></w:r><w:r wsp:rsidR="004879F4"><w:t>am held and firmly bound unto the State of Texas in the penal sum stated below for the payment of which sum well and truly to be made, and in addition all necessary and reasonable fees and expenses that may be incurred by peace officers in re-arresting me in the event the conditions of this bond are violated, I do bind myself, my heirs, executors and administrators, jointly and severally by these presents.</w:t></w:r></w:p><w:p wsp:rsidR="004879F4" wsp:rsidRDefault="004879F4"><w:pPr><w:tabs><w:tab w:val="right" w:pos="10710"/></w:tabs><w:spacing w:line="240" w:line-rule="exact"/></w:pPr><w:r><w:t>THE CONDITIONS OF THE ABOVE OBLIGATIONS ARE THAT I swear that I will appear before the </w:t></w:r><w:r wsp:rsidR="001741A0" wsp:rsidRPr="001741A0"><w:rPr><w:b/><w:u w:val="single"/></w:rPr><w:t>[Court]</w:t></w:r></w:p><w:p wsp:rsidR="004879F4" wsp:rsidRDefault="006C1A58"><w:pPr><w:tabs><w:tab w:val="right" w:pos="10710"/></w:tabs><w:spacing w:line="300" w:line-rule="exact"/></w:pPr><w:r><w:rPr><w:b/><w:noProof/><w:u w:val="single"/></w:rPr><w:t>[CourtLevel]</w:t></w:r><w:r><w:t> </w:t></w:r><w:r wsp:rsidR="004879F4"><w:t>at the Criminal Justice Center, </w:t></w:r><w:r wsp:rsidRPr="006C1A58"><w:rPr><w:b/><w:u w:val="single"/></w:rPr><w:t>[</w:t></w:r><w:r wsp:rsidRPr="006C1A58"><w:rPr><w:b/><w:noProof/><w:u w:val="single"/></w:rPr><w:t>Court Address]</w:t></w:r><w:r wsp:rsidR="007C4439"><w:rPr><w:b/><w:u w:val="single"/></w:rPr><w:t>, </w:t></w:r><w:r wsp:rsidR="004879F4"><w:t>Houston, Harris County, Texas, on the ________ of _____________________________, 20_____, at the hour of _______ A.M./P.M. or upon notice by the Court, or pay to the Court the principal sum of $ </w:t></w:r><w:r wsp:rsidR="001F045E" wsp:rsidRPr="001F045E"><w:rPr><w:b/><w:u w:val="single"/></w:rPr><w:t>[</w:t></w:r><w:r wsp:rsidR="001F045E" wsp:rsidRPr="001F045E"><w:rPr><w:b/><w:noProof/><w:u w:val="single"/></w:rPr><w:t>PersonalBondAmount]</w:t></w:r><w:r wsp:rsidR="004879F4"><w:t> plus all necessary and reasonable expenses incurred in any arrest for failure to appear.</w:t></w:r></w:p><w:p wsp:rsidR="004879F4" wsp:rsidRDefault="004879F4"><w:pPr><w:tabs><w:tab w:val="right" w:pos="10710"/></w:tabs><w:spacing w:line="240" w:line-rule="exact"/><w:ind w:first-line="432"/></w:pPr><w:r><w:t>I further swear that I will appear before any court or magistrate before whom this cause may hereinafter be pending at any time and place as may be required.</w:t></w:r></w:p><w:p wsp:rsidR="004879F4" wsp:rsidRDefault="004879F4"><w:pPr><w:tabs><w:tab w:val="right" w:pos="10710"/></w:tabs><w:spacing w:line="240" w:line-rule="exact"/><w:ind w:first-line="432"/></w:pPr><w:r><w:t>Now if I shall well and truly make said appearance before said Court, and there remain from day to day and term to term of said Court, until discharged by due course of law, then and there to answer said accusation against me, and further shall well and truly make my personal appearance in any and all subsequent proceedings that may be had relative to said charge in the course of the criminal action based on said charge, this obligation shall become void; Otherwise to remain in full force and effect.</w:t></w:r></w:p><w:p wsp:rsidR="004879F4" wsp:rsidRDefault="004879F4"><w:pPr><w:tabs><w:tab w:val="right" w:pos="10710"/></w:tabs><w:spacing w:line="240" w:line-rule="exact"/><w:ind w:first-line="432"/></w:pPr><w:r><w:t>I further understand that all or part of the information collected in the defendant report may be available to law enforcement or criminal justice personnel, including, but not limited to, the Judge or Magistrate hearing the case, the District Attorney’s Office, and the defense attorney of record in this cause.</w:t></w:r></w:p><w:p wsp:rsidR="004879F4" wsp:rsidRDefault="004879F4"><w:pPr><w:spacing w:line="200" w:line-rule="exact"/><w:rPr><w:sz w:val="16"/></w:rPr></w:pPr></w:p><w:p wsp:rsidR="004879F4" wsp:rsidRDefault="004879F4"><w:pPr><w:tabs><w:tab w:val="right" w:pos="10620"/></w:tabs></w:pPr><w:r><w:t>Fee=$ </w:t></w:r><w:r wsp:rsidR="00A43F29" wsp:rsidRPr="00A43F29"><w:rPr><w:b/><w:u w:val="single"/></w:rPr><w:t>[</w:t></w:r><w:r wsp:rsidR="00A43F29" wsp:rsidRPr="00A43F29"><w:rPr><w:b/><w:noProof/><w:u w:val="single"/></w:rPr><w:t>PBFee]</w:t></w:r><w:r wsp:rsidR="00496B62"><w:t>    </w:t></w:r><w:r><w:t>    Waived __________</w:t></w:r><w:r><w:tab wx:wTab="2310" wx:tlc="none" wx:cTlc="50"/><w:t>________________________________________________</w:t></w:r></w:p><w:p wsp:rsidR="004879F4" wsp:rsidRDefault="004879F4"><w:pPr><w:tabs><w:tab w:val="right" w:pos="9360"/><w:tab w:val="right" w:pos="10620"/></w:tabs></w:pPr><w:r><w:t>Special Conditions of bond in effect:   YES   /   NO</w:t></w:r><w:r><w:tab wx:wTab="3525" wx:tlc="none" wx:cTlc="77"/><w:t>Signature of Defendant </w:t></w:r><w:r><w:tab wx:wTab="1215" wx:tlc="none" wx:cTlc="26"/></w:r></w:p><w:p wsp:rsidR="004879F4" wsp:rsidRDefault="004879F4"><w:pPr><w:tabs><w:tab w:val="right" w:pos="10440"/><w:tab w:val="right" w:pos="10620"/></w:tabs><w:spacing w:before="120"/></w:pPr><w:r><w:tab wx:wTab="6705" wx:tlc="none" wx:cTlc="148"/><w:t>SWORN TO AND SUBSCRIBED BEFORE ME,</w:t></w:r></w:p><w:p wsp:rsidR="00DF5A36" wsp:rsidRDefault="00DF5A36" wsp:rsidP="00DF5A36"><w:pPr><w:tabs><w:tab w:val="right" w:pos="10620"/></w:tabs></w:pPr><w:r><w:t>APPROVED</w:t></w:r></w:p><w:p wsp:rsidR="004879F4" wsp:rsidRDefault="004879F4"><w:pPr><w:tabs><w:tab w:val="right" w:pos="10620"/></w:tabs></w:pPr><w:r><w:tab wx:wTab="5685" wx:tlc="none" wx:cTlc="125"/><w:t>this ______ day of _________________________, 20____.</w:t></w:r></w:p><w:p wsp:rsidR="004879F4" wsp:rsidRDefault="00DF5A36" wsp:rsidP="00DF5A36"><w:pPr><w:tabs><w:tab w:val="right" w:pos="10620"/></w:tabs><w:spacing w:before="240"/></w:pPr><w:r><w:t>___________________________________________________</w:t></w:r><w:r wsp:rsidR="004879F4"><w:tab wx:wTab="330" wx:tlc="none" wx:cTlc="6"/><w:t>_______________________________________________</w:t></w:r></w:p><w:p wsp:rsidR="004879F4" wsp:rsidRDefault="00DF5A36"><w:pPr><w:tabs><w:tab w:val="right" w:pos="9900"/><w:tab w:val="right" w:pos="10620"/></w:tabs></w:pPr><w:r><w:t>                                            JUDGE</w:t></w:r><w:r wsp:rsidR="004879F4"><w:tab wx:wTab="4140" wx:tlc="none" wx:cTlc="91"/><w:t>PERSONAL BOND OFFICE EMPLOYEE</w:t></w:r></w:p><w:p wsp:rsidR="004879F4" wsp:rsidRDefault="004879F4"><w:pPr><w:tabs><w:tab w:val="right" w:pos="9360"/><w:tab w:val="right" w:pos="10620"/></w:tabs></w:pPr><w:r><w:tab wx:wTab="7155" wx:tlc="none" wx:cTlc="158"/></w:r><st1:PlaceName w:st="on"><w:r><w:t>HARRIS</w:t></w:r></st1:PlaceName><w:r><w:t> </w:t></w:r><st1:PlaceName w:st="on"><w:r><w:t>COUNTY</w:t></w:r></st1:PlaceName><w:r><w:t>, </w:t></w:r><st1:place w:st="on"><st1:State w:st="on"><w:r><w:t>TEXAS</w:t></w:r></st1:State></st1:place></w:p><w:p wsp:rsidR="003A541E" wsp:rsidRDefault="003A541E" wsp:rsidP="003A541E"><w:pPr><w:autoSpaceDE w:val="off"/><w:autoSpaceDN w:val="off"/><w:adjustRightInd w:val="off"/><w:rPr><w:rFonts w:ascii="MS Shell Dlg" w:h-ansi="MS Shell Dlg" w:cs="Arial"/><wx:font wx:val="MS Shell Dlg"/><w:sz-cs w:val="17"/></w:rPr></w:pPr><w:r><w:rPr><w:rFonts w:ascii="Arial" w:h-ansi="Arial" w:cs="Arial"/><wx:font wx:val="Arial"/><w:sz-cs w:val="26"/></w:rPr><w:t>??????????????????????????????????????????????????????????????????????????????????????????????????</w:t></w:r></w:p><w:p wsp:rsidR="003A541E" wsp:rsidRDefault="003A541E" wsp:rsidP="003A541E"><w:pPr><w:tabs><w:tab w:val="left" w:pos="8010"/><w:tab w:val="right" w:pos="10620"/></w:tabs><w:jc w:val="center"/></w:pPr><w:r><w:t>IDENTIFICATION INFORMATION</w:t></w:r></w:p><w:p wsp:rsidR="003A541E" wsp:rsidRDefault="003A541E" wsp:rsidP="003A541E"><w:pPr><w:tabs><w:tab w:val="left" w:pos="6390"/><w:tab w:val="right" w:pos="10620"/></w:tabs></w:pPr><w:r><w:tab wx:wTab="6390" wx:tlc="none" wx:cTlc="141"/><w:t>Driver’s</w:t></w:r></w:p><w:p wsp:rsidR="003A541E" wsp:rsidRDefault="003A541E" wsp:rsidP="003A541E"><w:pPr><w:tabs><w:tab w:val="left" w:pos="8010"/><w:tab w:val="right" w:pos="10620"/></w:tabs></w:pPr><w:r><w:t>Date of Birth:</w:t></w:r><w:r><w:rPr><w:b/><w:noProof/><w:u w:val="single"/></w:rPr><w:t> [DateOfBirth]</w:t></w:r><w:r><w:t>   Place of Birth [PlaceOfBirth]</w:t></w:r><w:r><w:t>                         License # </w:t></w:r><w:r><w:rPr><w:b/><w:u w:val="single"/></w:rPr><w:t>[DriversLicense]</w:t></w:r><w:r><w:t>  </w:t></w:r><w:r><w:rPr><w:b/><w:u w:val="single"/></w:rPr><w:t>[DriversLicenseState]</w:t></w:r><w:r><w:t>   </w:t></w:r></w:p><w:p wsp:rsidR="003A541E" wsp:rsidRDefault="003A541E" wsp:rsidP="003A541E"><w:pPr><w:tabs><w:tab w:val="left" w:pos="8010"/><w:tab w:val="right" w:pos="10620"/></w:tabs><w:spacing w:line="300" w:line-rule="exact"/></w:pPr><w:r><w:t>Height </w:t></w:r><w:r><w:rPr><w:b/><w:u w:val="single"/></w:rPr><w:t>[Height]</w:t></w:r><w:r><w:t>   Weight </w:t></w:r><w:r><w:rPr><w:b/><w:u w:val="single"/></w:rPr><w:t>[Weight]</w:t></w:r><w:r><w:t>   Hair Color </w:t></w:r><w:r><w:rPr><w:b/><w:u w:val="single"/></w:rPr><w:t>[ColorOfHair]</w:t></w:r><w:r><w:t>  Eye Color </w:t></w:r><w:r><w:rPr><w:b/><w:u w:val="single"/></w:rPr><w:t>[ColorOfEye]</w:t></w:r></w:p><w:p wsp:rsidR="003A541E" wsp:rsidRDefault="003A541E" wsp:rsidP="003A541E"><w:pPr><w:tabs><w:tab w:val="left" w:pos="2160"/><w:tab w:val="left" w:pos="8010"/><w:tab w:val="right" w:pos="10620"/></w:tabs><w:spacing w:line="300" w:line-rule="exact"/><w:rPr><w:b/><w:u w:val="single"/></w:rPr></w:pPr><w:r><w:tab wx:wTab="2160" wx:tlc="none" wx:cTlc="47"/></w:r><w:r><w:rPr><w:b/><w:u w:val="single"/></w:rPr><w:t>[AddressStreet#] [AddressStreetName]</w:t></w:r><w:r><w:rPr><w:b/><w:u w:val="single"/></w:rPr><w:t>,  Apt: [AddressAptNumber]</w:t></w:r></w:p><w:p wsp:rsidR="003A541E" wsp:rsidRDefault="003A541E" wsp:rsidP="003A541E"><w:pPr><w:tabs><w:tab w:val="left" w:pos="2160"/><w:tab w:val="left" w:pos="8010"/><w:tab w:val="right" w:pos="10620"/></w:tabs></w:pPr><w:r><w:t>DEFENDANT</w:t></w:r><w:r><w:tab wx:wTab="1035" wx:tlc="none" wx:cTlc="22"/><w:t>Street Address</w:t></w:r></w:p><w:p wsp:rsidR="003A541E" wsp:rsidRDefault="003A541E" wsp:rsidP="003A541E"><w:pPr><w:tabs><w:tab w:val="left" w:pos="2160"/><w:tab w:val="left" w:pos="8010"/><w:tab w:val="right" w:pos="10620"/></w:tabs></w:pPr><w:r><w:t>MAILING</w:t></w:r><w:r><w:tab wx:wTab="1350" wx:tlc="none" wx:cTlc="29"/></w:r><w:r><w:rPr><w:b/><w:u w:val="single"/></w:rPr><w:t>[AddressCity]</w:t></w:r><w:r><w:rPr><w:b/><w:u w:val="single"/></w:rPr><w:t>,</w:t></w:r><w:r><w:rPr><w:b/></w:rPr><w:t> </w:t></w:r><w:r><w:rPr><w:b/><w:noProof/><w:u w:val="single"/></w:rPr><w:t>[AddressState]</w:t></w:r><w:r><w:rPr><w:b/><w:u w:val="single"/></w:rPr><w:t> [AddressZip]</w:t></w:r><w:r><w:rPr><w:b/><w:u w:val="single"/></w:rPr><w:t> [DefendantPhoneNumber]</w:t></w:r></w:p><w:p wsp:rsidR="003A541E" wsp:rsidRDefault="003A541E" wsp:rsidP="003A541E"><w:pPr><w:tabs><w:tab w:val="left" w:pos="2160"/><w:tab w:val="left" w:pos="7200"/><w:tab w:val="left" w:pos="8640"/><w:tab w:val="right" w:pos="10620"/></w:tabs></w:pPr><w:r><w:t>ADDRESS</w:t></w:r><w:r><w:tab wx:wTab="1305" wx:tlc="none" wx:cTlc="28"/></w:r><w:r><w:tab wx:wTab="5040" wx:tlc="none" wx:cTlc="111"/><w:t>Phone</w:t></w:r></w:p><w:p wsp:rsidR="003A541E" wsp:rsidRDefault="003A541E" wsp:rsidP="003A541E"><w:pPr><w:tabs><w:tab w:val="left" w:pos="5760"/><w:tab w:val="left" w:pos="8010"/><w:tab w:val="right" w:pos="10620"/></w:tabs></w:pPr><w:r><w:t>NEAREST RELATIVE</w:t></w:r><w:r><w:tab wx:wTab="3990" wx:tlc="none" wx:cTlc="88"/><w:t>DEFENDANT EMPLOYMENT INFORMATION</w:t></w:r></w:p><w:p wsp:rsidR="003A541E" wsp:rsidRDefault="003A541E" wsp:rsidP="003A541E"><w:pPr><w:tabs><w:tab w:val="left" w:pos="5760"/><w:tab w:val="left" w:pos="8010"/><w:tab w:val="right" w:pos="10620"/></w:tabs></w:pPr><w:r><w:t>Name ___________________________________________</w:t></w:r><w:r><w:tab wx:wTab="750" wx:tlc="none" wx:cTlc="16"/><w:t>Name </w:t></w:r><w:r><w:rPr><w:b/><w:u w:val="single"/></w:rPr><w:t>[Employer]</w:t></w:r></w:p><w:p wsp:rsidR="003A541E" wsp:rsidRDefault="003A541E" wsp:rsidP="003A541E"><w:pPr><w:tabs><w:tab w:val="left" w:pos="5760"/><w:tab w:val="left" w:pos="8010"/><w:tab w:val="right" w:pos="10620"/></w:tabs><w:rPr><w:b/><w:u w:val="single"/></w:rPr></w:pPr><w:r><w:t>Street ___________________________________________</w:t></w:r><w:r><w:tab wx:wTab="735" wx:tlc="none" wx:cTlc="15"/><w:t>Address </w:t></w:r><w:r><w:rPr><w:b/><w:u w:val="single"/></w:rPr><w:t>[EmployerStreet#] [EmployerAddressStreet]</w:t></w:r><w:r><w:rPr><w:b/><w:u w:val="single"/></w:rPr><w:t>,</w:t></w:r></w:p><w:p wsp:rsidR="003A541E" wsp:rsidRDefault="003A541E" wsp:rsidP="003A541E"><w:pPr><w:tabs><w:tab w:val="left" w:pos="5760"/><w:tab w:val="left" w:pos="8010"/><w:tab w:val="right" w:pos="10620"/></w:tabs><w:rPr><w:sz w:val="16"/><w:sz-cs w:val="16"/></w:rPr></w:pPr><w:r><w:rPr><w:b/></w:rPr><w:tab wx:wTab="5760" wx:tlc="none" wx:cTlc="127"/></w:r><w:r><w:rPr><w:b/><w:u w:val="single"/></w:rPr><w:t>[EmployerAddressCity]</w:t></w:r><w:r><w:rPr><w:b/><w:sz w:val="16"/><w:sz-cs w:val="16"/><w:u w:val="single"/></w:rPr><w:t>, [EmployerAddressState]</w:t></w:r><w:r><w:rPr><w:b/><w:sz w:val="16"/><w:sz-cs w:val="16"/><w:u w:val="single"/></w:rPr><w:t>, [EmployerAddressZip]</w:t></w:r></w:p><w:p wsp:rsidR="003A541E" wsp:rsidRDefault="003A541E" wsp:rsidP="003A541E"><w:pPr><w:tabs><w:tab w:val="left" w:pos="5760"/><w:tab w:val="left" w:pos="8010"/><w:tab w:val="right" w:pos="10620"/></w:tabs></w:pPr><w:r><w:t>City/State ________________________________________</w:t></w:r><w:r><w:tab wx:wTab="720" wx:tlc="none" wx:cTlc="15"/><w:t>Phone  </w:t></w:r><w:r><w:rPr><w:b/><w:noProof/><w:u w:val="single"/></w:rPr><w:t>[EmployerPhone]</w:t></w:r></w:p><w:p wsp:rsidR="003A541E" wsp:rsidRDefault="003A541E" wsp:rsidP="003A541E"><w:pPr><w:autoSpaceDE w:val="off"/><w:autoSpaceDN w:val="off"/><w:adjustRightInd w:val="off"/><w:rPr><w:rFonts w:ascii="MS Shell Dlg" w:h-ansi="MS Shell Dlg" w:cs="Arial"/><wx:font wx:val="MS Shell Dlg"/><w:sz-cs w:val="17"/></w:rPr></w:pPr><w:r><w:rPr><w:rFonts w:ascii="Arial" w:h-ansi="Arial" w:cs="Arial"/><wx:font wx:val="Arial"/><w:sz-cs w:val="26"/></w:rPr><w:t>??????????????????????????????????????????????????????????????????????????????????????????????????</w:t></w:r></w:p><w:p wsp:rsidR="004879F4" wsp:rsidRDefault="004879F4"><w:pPr><w:tabs><w:tab w:val="left" w:pos="5760"/><w:tab w:val="left" w:pos="8010"/><w:tab w:val="right" w:pos="10620"/></w:tabs></w:pPr><w:r><w:t>Filed with _________________ on ___________________________ at ___________________ A.M./P.M. by: __________________</w:t></w:r></w:p><w:p wsp:rsidR="004879F4" wsp:rsidRDefault="004879F4"><w:pPr><w:tabs><w:tab w:val="left" w:pos="5760"/><w:tab w:val="left" w:pos="8010"/><w:tab w:val="right" w:pos="10620"/></w:tabs><w:spacing w:line="300" w:line-rule="exact"/></w:pPr><w:r><w:t>Defendant Notified ________________________   HPD _____________   HCJ _____________   Non-Arrest ____________</w:t></w:r></w:p><w:sectPr wsp:rsidR="004879F4" wsp:rsidSect="00FE035B"><w:ftr w:type="odd"><w:p wsp:rsidR="00496B62" wsp:rsidRDefault="00496B62"><w:pPr><w:pStyle w:val="Footer"/><w:rPr><w:sz w:val="16"/></w:rPr></w:pPr><w:r><w:rPr><w:sz w:val="16"/></w:rPr><w:t>Rev 3/9/2004</w:t></w:r></w:p></w:ftr><w:pgSz w:w="12240" w:h="15840" w:code="1"/><w:pgMar w:top="720" w:right="720" w:bottom="720" w:left="720" w:header="360" w:footer="360" w:gutter="0"/><w:cols w:space="720"/></w:sectPr></wx:sub-section></wx:sect></w:body></w:wordDocument>